{
    "projectId": 1,
    "templateId": 2,
    "subtemplateId": 1827184074989514763,
    "data":[
      {
      "basicInformation": ["310300","单向双车道道路","无绿植","条"],
      "startYearData": 798.0,
      "endYearData": [0.0,0.0,0.0,0.0,0.0,0.0,0.0]
      },
      {
        "basicInformation": ["310301","双向双车道道路","无绿植","条"],
        "startYearData": 650.0,
        "endYearData": [450.0,350.0,0.0,0.0,0.0,0.0,0.0]
      },
      {
        "basicInformation": ["310800","单向双车道道路","无绿植","条"],
        "startYearData": 530.0,
        "endYearData": [350.0,250.0,0.0,0.0,0.0,0.0,0.0]
      }
    ]
}
